ChangeLog.md
LICENSE
MANIFEST.in
README.md
SECURITY.md
TESTING.md
requirements.txt
setup.py
tox.ini
impacket/Dot11Crypto.py
impacket/Dot11KeyManager.py
impacket/ICMP6.py
impacket/IP6.py
impacket/IP6_Address.py
impacket/IP6_Extension_Headers.py
impacket/ImpactDecoder.py
impacket/ImpactPacket.py
impacket/NDP.py
impacket/__init__.py
impacket/cdp.py
impacket/crypto.py
impacket/dhcp.py
impacket/dns.py
impacket/dot11.py
impacket/dpapi.py
impacket/eap.py
impacket/ese.py
impacket/helper.py
impacket/hresult_errors.py
impacket/http.py
impacket/mapi_constants.py
impacket/mqtt.py
impacket/nmb.py
impacket/nt_errors.py
impacket/ntlm.py
impacket/pcap_linktypes.py
impacket/pcapfile.py
impacket/smb.py
impacket/smb3.py
impacket/smb3structs.py
impacket/smbconnection.py
impacket/smbserver.py
impacket/spnego.py
impacket/structure.py
impacket/system_errors.py
impacket/tds.py
impacket/uuid.py
impacket/version.py
impacket/winregistry.py
impacket/wps.py
impacket_no_examples.egg-info/PKG-INFO
impacket_no_examples.egg-info/SOURCES.txt
impacket_no_examples.egg-info/dependency_links.txt
impacket_no_examples.egg-info/requires.txt
impacket_no_examples.egg-info/top_level.txt
tests/__init__.py
tests/conftest.py
tests/dcetests.cfg.template
tests/walkmodules.py
tests/ImpactPacket/__init__.py
tests/ImpactPacket/test_ICMP6.py
tests/ImpactPacket/test_IP6.py
tests/ImpactPacket/test_IP6_Address.py
tests/ImpactPacket/test_IP6_Extension_Headers.py
tests/ImpactPacket/test_TCP.py
tests/ImpactPacket/test_TCP_bug_issue7.py
tests/ImpactPacket/test_ethernet.py
tests/SMB_RPC/__init__.py
tests/SMB_RPC/test_ldap.py
tests/SMB_RPC/test_ndr.py
tests/SMB_RPC/test_nmb.py
tests/SMB_RPC/test_ntlm.py
tests/SMB_RPC/test_rpch.py
tests/SMB_RPC/test_rpcrt.py
tests/SMB_RPC/test_secretsdump.py
tests/SMB_RPC/test_smb.py
tests/SMB_RPC/test_smbserver.py
tests/SMB_RPC/test_spnego.py
tests/SMB_RPC/test_wmi.py
tests/data/ccache-v1
tests/data/ccache-v2
tests/data/ccache-v3
tests/data/ccache-v3-kirbi
tests/data/ccache-v4
tests/data/ccache-v4-kirbi
tests/dcerpc/__init__.py
tests/dcerpc/test_bkrp.py
tests/dcerpc/test_dcomrt.py
tests/dcerpc/test_dhcpm.py
tests/dcerpc/test_drsuapi.py
tests/dcerpc/test_epm.py
tests/dcerpc/test_even.py
