Metadata-Version: 2.1
Name: impacket-no-examples
Version: 0.10.2
Summary: Network protocols Constructors and Dissectors without examples
Home-page: https://github.com/dar-suridata/impacket-no-examples
Author: SecureAuth Corporation
Maintainer: dars2k
License: Apache modified
Platform: Unix
Platform: Windows
Classifier: Programming Language :: Python :: 3.9
Classifier: Programming Language :: Python :: 3.8
Classifier: Programming Language :: Python :: 3.7
Classifier: Programming Language :: Python :: 3.6
Provides-Extra: pyreadline
License-File: LICENSE
